{
  "model_name": "minmax_02_pca_0.98_xgboost_native",
  "metrics": {
    "accuracy": 0.7090281771132835,
    "weighted_precision": 0.7113072258747026,
    "weighted_recall": 0.7090281771132835,
    "weighted_f1": 0.7084230605288739,
    "timestamp": "2025-09-18T06:24:07.518964"
  },
  "model_path": "/content/btl1_20250918_061900/models/minmax_02_pca_0.98_xgboost_native.joblib",
  "components": {
    "scaler": "ComponentConfig(name='standard_scaler', factory_func=<function RobustConfigurator._register_default_components.<locals>.<lambda> at 0x78f632de27a0>, params={}, description='Standard Scaler (mean=0, std=1)', dependencies=[], conflicts=[])",
    "model": "ComponentConfig(name='logistic', factory_func=<function RobustConfigurator._register_default_components.<locals>.<lambda> at 0x78f63566d4e0>, params={}, description='Logistic Regression', dependencies=[], conflicts=[])"
  },
  "features": {
    "numeric": [
      "Age",
      "RoomService",
      "FoodCourt",
      "ShoppingMall",
      "Spa",
      "VRDeck",
      "Num",
      "Group"
    ],
    "categorical": [
      "Member",
      "HomePlanet",
      "CryoSleep",
      "Deck",
      "Side",
      "Destination",
      "VIP"
    ]
  }
}